pyclaapi-0.1.9.dist-info/METADATA
pyclaapi-0.1.9.dist-info/WHEEL
pyclaapi/__init__.py
pyclaapi/api.py
pyclaapi/model.py
pyclaapi/pyclaapi.py
pyclaapi-0.1.9.dist-info/RECORD
