Metadata-Version: 2.1
Name: PyClaAPI
Version: 0.1.9
Summary: A Python library for Clash API.
Author-Email: KuTaKe <kuttake@outlook.com>
License: MIT
Requires-Python: >=3.8
Requires-Dist: httpx
